detection/__init__.py
detection/detection.py
textdetection/__init__.py
textdetection/detection.py
textdetection-0.2.1.dist-info/LICENSE
textdetection-0.2.1.dist-info/METADATA
textdetection-0.2.1.dist-info/WHEEL
textdetection-0.2.1.dist-info/top_level.txt
textdetection-0.2.1.dist-info/RECORD
