Metadata-Version: 2.1
Name: textdetection
Version: 0.2.1
Summary: A blackbox detection on text against adversarial attacks
Home-page: https://github.com/threemmm/text-blackbox-detection
Author: Mohammad Maghsoudi
Author-email: maghsoudismtp@gmail.com
License: UNKNOWN
Platform: UNKNOWN
Classifier: Programming Language :: Python :: 3
Classifier: License :: OSI Approved :: MIT License
Classifier: Operating System :: OS Independent
Requires-Python: >=3.4
